python_11_40_modules/__init__.py
python_11_40_modules/app.py
python_11_40_modules/operation/__init__.py
python_11_40_modules/operation/number.py
python_11_40_modules-0.1.0.dist-info/METADATA
python_11_40_modules-0.1.0.dist-info/WHEEL
python_11_40_modules-0.1.0.dist-info/RECORD
