Metadata-Version: 2.1
Name: python-11-40-modules
Version: 0.1.0
Summary: 
Author: Krzysztof
Author-email: programowanie.krzysiek@gmail.com
Requires-Python: >=3.11,<4.0
Classifier: Programming Language :: Python :: 3
Classifier: Programming Language :: Python :: 3.11
Requires-Dist: django (>=4.2.1,<5.0.0)
